AAM/AA_class.py
AAM/AA_result_class.py
AAM/CAA_class.py
AAM/OAA_class.py
AAM/RBOAA_class.py
AAM/TSAA_class.py
AAM/__init__.py
AAM/loading_bar_class.py
AAM/plots_class.py
AAM/synthetic_data_class.py
AA_module-1.2.0.dist-info/LICENSE.txt
AA_module-1.2.0.dist-info/METADATA
AA_module-1.2.0.dist-info/WHEEL
AA_module-1.2.0.dist-info/top_level.txt
AA_module-1.2.0.dist-info/RECORD
