Metadata-Version: 2.1
Name: AA-module
Version: 1.2.0
Summary: Module for performing various archetypal analyses.
Home-page: https://github.com/anden1305/AAM-Module
Author: Andreas Bigom, Michael Harborg, Oliver Elmgren & Marcus Presutti
Author-email: andreasbigom@gmail.com
License: MIT
Project-URL: repository, https://github.com/anden1305/AAM-Module
Keywords: Archetypal Analysis
Classifier: Programming Language :: Python :: 3
Classifier: License :: OSI Approved :: MIT License
Classifier: Operating System :: OS Independent
Requires-Python: >=3.9.7
License-File: LICENSE.txt
Requires-Dist: pandas
Requires-Dist: numpy
Requires-Dist: matplotlib
Requires-Dist: torch
Requires-Dist: scipy
Requires-Dist: sklearn
